{
    "key": "group_5e5d79a9aeacf",
    "title": "Video post type fields",
    "fields": [
        {
            "key": "field_5ec404cdfe7ea",
            "label": "Video source",
            "name": "post_video_source",
            "type": "radio",
            "instructions": "",
            "required": 0,
            "conditional_logic": 0,
            "wrapper": {
                "width": "",
                "class": "",
                "id": ""
            },
            "choices": {
                "youtube": "Youtube",
                "vimeo": "Vimeo"
            },
            "allow_null": 0,
            "other_choice": 0,
            "default_value": "youtube",
            "layout": "horizontal",
            "return_format": "value",
            "save_other_choice": 0
        },
        {
            "key": "field_5e5d79b251bb9",
            "label": "Youtube Video ID",
            "name": "video_embed_code",
            "type": "text",
            "instructions": "",
            "required": 0,
            "conditional_logic": 0,
            "wrapper": {
                "width": "",
                "class": "",
                "id": ""
            },
            "default_value": "",
            "placeholder": "",
            "prepend": "",
            "append": "",
            "maxlength": ""
        },
        {
            "key": "field_5ec404fefe7eb",
            "label": "Vimeo Video ID",
            "name": "vimeo_video_id",
            "type": "text",
            "instructions": "",
            "required": 0,
            "conditional_logic": [
                [
                    {
                        "field": "field_5ec404cdfe7ea",
                        "operator": "==",
                        "value": "vimeo"
                    }
                ]
            ],
            "wrapper": {
                "width": "",
                "class": "",
                "id": ""
            },
            "default_value": "",
            "placeholder": "",
            "prepend": "",
            "append": "",
            "maxlength": ""
        },
        {
            "key": "field_5e82346cf2317",
            "label": "Custom video thumbnail",
            "name": "vid-thumb",
            "type": "image",
            "instructions": "Replaces the default thumbnail pulled from Youtube",
            "required": 0,
            "conditional_logic": 0,
            "wrapper": {
                "width": "",
                "class": "",
                "id": ""
            },
            "return_format": "url",
            "preview_size": "medium",
            "library": "all",
            "min_width": "",
            "min_height": "",
            "min_size": "",
            "max_width": "",
            "max_height": "",
            "max_size": "",
            "mime_types": ""
        }
    ],
    "location": [
        [
            {
                "param": "post_type",
                "operator": "==",
                "value": "video"
            }
        ]
    ],
    "menu_order": 0,
    "position": "normal",
    "style": "default",
    "label_placement": "top",
    "instruction_placement": "label",
    "hide_on_screen": "",
    "active": 1,
    "description": "",
    "modified": 1589904671
}